pirates/__init__.py
pirates/apps.py
pirates/auth.py
pirates/models.py
pirates/signals.py
pirates/urls.py
pirates-0.7.0.dist-info/LICENSE
pirates-0.7.0.dist-info/METADATA
pirates-0.7.0.dist-info/WHEEL
pirates-0.7.0.dist-info/RECORD
