Metadata-Version: 2.1
Name: pirates
Version: 0.7.0
Summary: Django app for users, teams and groups.
Home-page: https://gitlab.pirati.cz/to/pirates
License: MIT
Keywords: django,openid,sso
Author: Jan Bednařík
Author-email: jan.bednarik@gmail.com
Requires-Python: >=3.8,<4.0
Classifier: Development Status :: 5 - Production/Stable
Classifier: Framework :: Django
Classifier: Framework :: Django :: 3.0
Classifier: Framework :: Django :: 3.1
Classifier: Framework :: Django :: 3.2
Classifier: Framework :: Django :: 4.0
Classifier: Intended Audience :: Developers
Classifier: License :: OSI Approved :: MIT License
Classifier: Operating System :: OS Independent
Classifier: Programming Language :: Python
Classifier: Programming Language :: Python :: 3
Classifier: Programming Language :: Python :: 3.8
Classifier: Programming Language :: Python :: 3.9
Classifier: Programming Language :: Python :: 3.10
Classifier: Programming Language :: Python :: 3.11
Classifier: Programming Language :: Python :: Implementation :: CPython
Classifier: Topic :: Utilities
Requires-Dist: mozilla-django-oidc (>=3.0.0,<4)
Project-URL: Repository, https://gitlab.pirati.cz/to/pirates
